__init__.py
customexception.py
db_config.py
log.py
sendmail.py
dto/custom_exception_model_dto.py
setuutility-0.0.5.dist-info/METADATA
setuutility-0.0.5.dist-info/WHEEL
setuutility-0.0.5.dist-info/RECORD
