Metadata-Version: 2.1
Name: SETUUtility
Version: 0.0.5
Summary: Package of common functionality used in cloud functions
Author-email: SETU_Team <author@example.com>
Classifier: License :: OSI Approved :: MIT License
Classifier: Operating System :: OS Independent
Classifier: Programming Language :: Python :: 3
Requires-Python: >=3.9
